polimer/__init__.py
polimer-0.0.2.dist-info/LICENSE
polimer-0.0.2.dist-info/METADATA
polimer-0.0.2.dist-info/WHEEL
polimer-0.0.2.dist-info/top_level.txt
polimer-0.0.2.dist-info/RECORD
