Metadata-Version: 2.1
Name: polimer
Version: 0.0.2
Summary: Automated callstack synthesis framework (annotations-based)
Author-email: Aleksey Boev <boev.aleksey@gmail.com>
Project-URL: Homepage, https://github.com/aboev/polimer
Project-URL: Issues, https://github.com/aboev/polimer/issues
Classifier: Programming Language :: Python :: 3
Classifier: License :: OSI Approved :: MIT License
Classifier: Operating System :: OS Independent
Requires-Python: >=3.8
License-File: LICENSE
